{
  "slug": "mine",
  "name": "Vahe Muradyan",
  "subtitle": "Animator · character design · story & motion",
  "accent": "#ff6b4a",
  "coverImage": "",
  "artStructure": {
    "portfolioTitle": "Art Structure Portfolio",
    "coverImage": "",
    "works": [
      {
        "id": "as-01",
        "title": "Artwork 1",
        "date": "",
        "media": "",
        "category": "drawing",
        "image": "",
        "images": [],
        "processImages": [],
        "artistStatement": ""
      },
      {
        "id": "as-02",
        "title": "Artwork 2",
        "date": "",
        "media": "",
        "category": "painting",
        "image": "",
        "images": [],
        "processImages": [],
        "artistStatement": ""
      },
      {
        "id": "as-03",
        "title": "Artwork 3",
        "date": "",
        "media": "",
        "category": "mixed-media",
        "image": "",
        "images": [],
        "processImages": [],
        "artistStatement": ""
      },
      {
        "id": "as-04",
        "title": "Artwork 4",
        "date": "",
        "media": "",
        "category": "digital",
        "image": "",
        "images": [],
        "processImages": [],
        "artistStatement": ""
      },
      {
        "id": "as-05",
        "title": "Artwork 5",
        "date": "",
        "media": "",
        "category": "sculpture-3d",
        "image": "",
        "images": [],
        "processImages": [],
        "artistStatement": ""
      },
      {
        "id": "as-06",
        "title": "Artwork 6",
        "date": "",
        "media": "",
        "category": "sketchbook-process",
        "image": "",
        "images": [],
        "processImages": [],
        "artistStatement": ""
      },
      {
        "id": "as-07",
        "title": "Artwork 7",
        "date": "",
        "media": "",
        "category": "other",
        "image": "",
        "images": [],
        "processImages": [],
        "artistStatement": ""
      }
    ]
  },
  "works": [
    {
      "id": "work-01",
      "title": "Artwork 1",
      "media": "",
      "category": "character-design",
      "description": "",
      "image": ""
    },
    {
      "id": "work-02",
      "title": "Artwork 2",
      "media": "",
      "category": "character-design",
      "description": "",
      "image": ""
    },
    {
      "id": "work-03",
      "title": "Artwork 3",
      "media": "",
      "category": "drawing-painting",
      "description": "",
      "image": ""
    },
    {
      "id": "work-04",
      "title": "Artwork 4",
      "media": "",
      "category": "drawing-painting",
      "description": "",
      "image": ""
    },
    {
      "id": "work-05",
      "title": "Artwork 5",
      "media": "",
      "category": "backgrounds-props",
      "description": "",
      "image": ""
    },
    {
      "id": "work-06",
      "title": "Artwork 6",
      "media": "",
      "category": "backgrounds-props",
      "description": "",
      "image": ""
    },
    {
      "id": "work-07",
      "title": "Artwork 7",
      "media": "",
      "category": "digital-illustration",
      "description": "",
      "image": ""
    },
    {
      "id": "work-08",
      "title": "Artwork 8",
      "media": "",
      "category": "digital-illustration",
      "description": "",
      "image": ""
    },
    {
      "id": "work-09",
      "title": "Artwork 9",
      "media": "",
      "category": "more-work",
      "description": "",
      "image": ""
    },
    {
      "id": "work-10",
      "title": "Artwork 10",
      "media": "",
      "category": "more-work",
      "description": "",
      "image": "",
      "images": []
    }
  ],
  "animations": [
    {
      "id": "anim-01",
      "title": "Animation 1 — Main Film",
      "media": "",
      "description": "",
      "video": "",
      "still": "",
      "progress": {
        "title": "Behind the scenes",
        "description": "",
        "storyboard": "",
        "images": [],
        "video": ""
      }
    },
    {
      "id": "anim-02",
      "title": "Animation 2",
      "media": "",
      "description": "",
      "video": "",
      "still": ""
    },
    {
      "id": "anim-03",
      "title": "Animation 3",
      "media": "",
      "description": "",
      "video": "",
      "still": ""
    }
  ]
}
